README.md
setup.py
onenet/__init__.py
onenet/__version__.py
onenet.egg-info/PKG-INFO
onenet.egg-info/SOURCES.txt
onenet.egg-info/dependency_links.txt
onenet.egg-info/top_level.txt